CHANGES.txt
LICENSE.txt
MANIFEST.in
README.rst
setup.py
yoapi/__init__.py
yoapi/yo.py
yoapi.egg-info/PKG-INFO
yoapi.egg-info/SOURCES.txt
yoapi.egg-info/dependency_links.txt
yoapi.egg-info/requires.txt
yoapi.egg-info/top_level.txt