Metadata-Version: 1.0
Name: yoapi
Version: 1.1
Summary: Python YoApi.
Home-page: http://github.com/gizmoguy/python-yoapi
Author: Brad Cowie
Author-email: brad@gizmoguy.net.nz
License: Apache 2.0
Platform: UNKNOWN
